audiosub/__init__.py
audiosub-0.3.dist-info/METADATA
audiosub-0.3.dist-info/WHEEL
audiosub-0.3.dist-info/entry_points.txt
audiosub-0.3.dist-info/RECORD
