Metadata-Version: 2.4
Name: audiosub
Version: 0.3
Summary: A command-line tool for generating subtitles from audio file using mlx-whisper
Project-URL: Homepage, https://github.com/huccihuang/audiosub
Project-URL: Repository, https://github.com/huccihuang/audiosub
Requires-Python: >=3.12
Requires-Dist: click>=8.3.0
Requires-Dist: mlx-whisper>=0.4.3
